py_aga/__init__.py
py_aga/aga.py
py_aga-0.1.4.dist-info/METADATA
py_aga-0.1.4.dist-info/WHEEL
py_aga-0.1.4.dist-info/licenses/LICENSE
py_aga-0.1.4.dist-info/RECORD
