Metadata-Version: 2.1
Name: py_aga
Version: 0.1.4
Summary: Lightweight native Python command-line interface argument builder
Project-URL: Homepage, https://github.com/amitchone/py-aga
Project-URL: Documentation, https://github.com/amitchone/py-aga/blob/main/README.md
Project-URL: Changes, https://github.com/amitchone/py-aga
Author-email: Adam Mitchell <adamstuartmitchell@gmail.com>
License:                                  Apache License
License-File: LICENSE
Classifier: Development Status :: 3 - Alpha
Classifier: Intended Audience :: Developers
Classifier: License :: OSI Approved :: Apache Software License
Classifier: Operating System :: OS Independent
Classifier: Programming Language :: Python :: 3.9
Classifier: Programming Language :: Python :: 3.10
Classifier: Programming Language :: Python :: 3.11
Classifier: Programming Language :: Python :: 3.12
Classifier: Programming Language :: Python :: 3.13
Requires-Python: >=3.9
